{
  "shapes": [
    {
      "label": "target",
      "points": [
        [
          480,
          508
        ],
        [
          481,
          509
        ],
        [
          482,
          508
        ]
      ]
    },
    {
      "label": "target",
      "points": [
        [
          409,
          508
        ],
        [
          409,
          510
        ],
        [
          410,
          510
        ],
        [
          411,
          509
        ],
        [
          410,
          508
        ]
      ]
    },
    {
      "label": "target",
      "points": [
        [
          125,
          508
        ],
        [
          126,
          509
        ],
        [
          127,
          509
        ],
        [
          127,
          508
        ]
      ]
    },
    {
      "label": "target",
      "points": [
        [
          497,
          497
        ],
        [
          497,
          499
        ],
        [
          499,
          499
        ]
      ]
    },
    {
      "label": "target",
      "points": [
        [
          466,
          492
        ],
        [
          467,
          493
        ],
        [
          469,
          493
        ],
        [
          469,
          492
        ]
      ]
    },
    {
      "label": "target",
      "points": [
        [
          481,
          488
        ],
        [
          480,
          489
        ],
        [
          481,
          490
        ],
        [
          481,
          491
        ],
        [
          482,
          491
        ],
        [
          482,
          490
        ],
        [
          481,
          489
        ]
      ]
    },
    {
      "label": "target",
      "points": [
        [
          361,
          479
        ],
        [
          360,
          480
        ],
        [
          360,
          482
        ],
        [
          361,
          483
        ],
        [
          362,
          482
        ],
        [
          362,
          480
        ]
      ]
    },
    {
      "label": "target",
      "points": [
        [
          374,
          471
        ],
        [
          373,
          472
        ],
        [
          373,
          473
        ],
        [
          374,
          474
        ],
        [
          374,
          475
        ],
        [
          375,
          475
        ],
        [
          375,
          471
        ]
      ]
    },
    {
      "label": "target",
      "points": [
        [
          496,
          465
        ],
        [
          496,
          468
        ],
        [
          495,
          469
        ],
        [
          495,
          470
        ],
        [
          496,
          471
        ],
        [
          496,
          491
        ],
        [
          497,
          492
        ],
        [
          497,
          493
        ],
        [
          496,
          494
        ],
        [
          497,
          495
        ],
        [
          497,
          493
        ],
        [
          498,
          492
        ],
        [
          501,
          493
        ],
        [
          500,
          492
        ],
        [
          500,
          490
        ],
        [
          499,
          490
        ],
        [
          497,
          488
        ],
        [
          499,
          486
        ],
        [
          500,
          487
        ],
        [
          501,
          486
        ],
        [
          501,
          484
        ],
        [
          500,
          483
        ],
        [
          500,
          482
        ],
        [
          497,
          479
        ],
        [
          499,
          477
        ],
        [
          500,
          478
        ],
        [
          501,
          478
        ],
        [
          501,
          476
        ],
        [
          499,
          473
        ],
        [
          500,
          470
        ],
        [
          497,
          466
        ],
        [
          497,
          465
        ]
      ]
    },
    {
      "label": "target",
      "points": [
        [
          364,
          465
        ],
        [
          365,
          466
        ],
        [
          365,
          467
        ],
        [
          366,
          468
        ],
        [
          367,
          468
        ],
        [
          367,
          466
        ],
        [
          366,
          465
        ]
      ]
    },
    {
      "label": "target",
      "points": [
        [
          377,
          459
        ],
        [
          376,
          461
        ],
        [
          380,
          463
        ],
        [
          380,
          465
        ],
        [
          378,
          466
        ],
        [
          380,
          469
        ],
        [
          378,
          475
        ],
        [
          379,
          478
        ],
        [
          377,
          480
        ],
        [
          374,
          478
        ],
        [
          373,
          483
        ],
        [
          376,
          484
        ],
        [
          378,
          486
        ],
        [
          378,
          489
        ],
        [
          385,
          493
        ],
        [
          388,
          496
        ],
        [
          388,
          498
        ],
        [
          396,
          503
        ],
        [
          396,
          508
        ],
        [
          399,
          511
        ],
        [
          402,
          511
        ],
        [
          403,
          509
        ],
        [
          402,
          506
        ],
        [
          405,
          504
        ],
        [
          406,
          501
        ],
        [
          408,
          502
        ],
        [
          409,
          500
        ],
        [
          406,
          501
        ],
        [
          403,
          498
        ],
        [
          401,
          493
        ],
        [
          397,
          492
        ],
        [
          395,
          490
        ],
        [
          395,
          488
        ],
        [
          392,
          487
        ],
        [
          392,
          485
        ],
        [
          389,
          481
        ],
        [
          392,
          473
        ],
        [
          393,
          465
        ],
        [
          384,
          464
        ],
        [
          382,
          466
        ],
        [
          379,
          460
        ]
      ]
    },
    {
      "label": "target",
      "points": [
        [
          505,
          443
        ],
        [
          505,
          451
        ],
        [
          504,
          452
        ],
        [
          504,
          472
        ],
        [
          505,
          473
        ],
        [
          503,
          477
        ],
        [
          504,
          480
        ],
        [
          503,
          483
        ],
        [
          504,
          501
        ],
        [
          503,
          502
        ],
        [
          504,
          503
        ],
        [
          504,
          511
        ],
        [
          511,
          511
        ],
        [
          509,
          507
        ],
        [
          509,
          504
        ],
        [
          511,
          503
        ],
        [
          509,
          497
        ],
        [
          511,
          495
        ],
        [
          510,
          489
        ],
        [
          511,
          483
        ],
        [
          509,
          481
        ],
        [
          511,
          479
        ],
        [
          511,
          476
        ],
        [
          509,
          474
        ],
        [
          511,
          472
        ],
        [
          511,
          468
        ],
        [
          509,
          467
        ],
        [
          509,
          464
        ],
        [
          511,
          461
        ],
        [
          508,
          458
        ],
        [
          510,
          453
        ],
        [
          508,
          451
        ],
        [
          507,
          452
        ],
        [
          505,
          451
        ],
        [
          505,
          446
        ],
        [
          508,
          445
        ]
      ]
    },
    {
      "label": "target",
      "points": [
        [
          505,
          436
        ],
        [
          505,
          438
        ],
        [
          506,
          437
        ],
        [
          508,
          437
        ],
        [
          508,
          436
        ]
      ]
    },
    {
      "label": "target",
      "points": [
        [
          473,
          404
        ],
        [
          473,
          405
        ],
        [
          474,
          405
        ]
      ]
    },
    {
      "label": "target",
      "points": [
        [
          368,
          401
        ],
        [
          366,
          403
        ],
        [
          365,
          403
        ],
        [
          360,
          409
        ],
        [
          358,
          410
        ],
        [
          357,
          413
        ],
        [
          359,
          413
        ],
        [
          360,
          412
        ],
        [
          362,
          413
        ],
        [
          362,
          416
        ],
        [
          365,
          421
        ],
        [
          365,
          424
        ],
        [
          370,
          430
        ],
        [
          370,
          433
        ],
        [
          373,
          437
        ],
        [
          373,
          442
        ],
        [
          377,
          442
        ],
        [
          378,
          441
        ],
        [
          375,
          437
        ],
        [
          375,
          433
        ],
        [
          372,
          430
        ],
        [
          372,
          420
        ],
        [
          371,
          419
        ],
        [
          371,
          413
        ],
        [
          368,
          407
        ],
        [
          368,
          404
        ],
        [
          369,
          403
        ]
      ]
    },
    {
      "label": "target",
      "points": [
        [
          111,
          397
        ],
        [
          110,
          397
        ],
        [
          109,
          398
        ],
        [
          108,
          398
        ],
        [
          108,
          399
        ],
        [
          111,
          399
        ]
      ]
    },
    {
      "label": "target",
      "points": [
        [
          109,
          388
        ],
        [
          109,
          389
        ],
        [
          108,
          390
        ],
        [
          109,
          391
        ],
        [
          111,
          391
        ],
        [
          111,
          389
        ],
        [
          110,
          388
        ]
      ]
    },
    {
      "label": "target",
      "points": [
        [
          464,
          387
        ],
        [
          457,
          392
        ],
        [
          453,
          403
        ],
        [
          453,
          426
        ],
        [
          448,
          424
        ],
        [
          434,
          433
        ],
        [
          426,
          469
        ],
        [
          412,
          473
        ],
        [
          417,
          483
        ],
        [
          413,
          501
        ],
        [
          420,
          511
        ],
        [
          476,
          509
        ],
        [
          464,
          506
        ],
        [
          468,
          505
        ],
        [
          465,
          501
        ],
        [
          471,
          501
        ],
        [
          463,
          498
        ],
        [
          464,
          485
        ],
        [
          471,
          485
        ],
        [
          469,
          474
        ],
        [
          477,
          469
        ],
        [
          474,
          466
        ],
        [
          477,
          462
        ],
        [
          481,
          464
        ],
        [
          480,
          469
        ],
        [
          483,
          469
        ],
        [
          481,
          464
        ],
        [
          487,
          462
        ],
        [
          490,
          475
        ],
        [
          491,
          461
        ],
        [
          481,
          456
        ],
        [
          477,
          460
        ],
        [
          478,
          453
        ],
        [
          454,
          429
        ],
        [
          467,
          429
        ],
        [
          463,
          426
        ],
        [
          467,
          420
        ],
        [
          463,
          419
        ],
        [
          461,
          402
        ]
      ]
    },
    {
      "label": "target",
      "points": [
        [
          470,
          378
        ],
        [
          468,
          378
        ],
        [
          467,
          379
        ],
        [
          467,
          381
        ],
        [
          466,
          382
        ],
        [
          468,
          382
        ],
        [
          468,
          381
        ],
        [
          469,
          380
        ],
        [
          470,
          380
        ]
      ]
    },
    {
      "label": "target",
      "points": [
        [
          127,
          376
        ],
        [
          126,
          376
        ],
        [
          124,
          378
        ],
        [
          124,
          379
        ],
        [
          125,
          380
        ],
        [
          125,
          382
        ],
        [
          126,
          382
        ],
        [
          127,
          381
        ]
      ]
    },
    {
      "label": "target",
      "points": [
        [
          440,
          373
        ],
        [
          440,
          374
        ],
        [
          439,
          375
        ],
        [
          439,
          377
        ],
        [
          440,
          378
        ],
        [
          440,
          379
        ],
        [
          441,
          379
        ],
        [
          442,
          378
        ],
        [
          442,
          375
        ],
        [
          441,
          374
        ],
        [
          441,
          373
        ]
      ]
    },
    {
      "label": "target",
      "points": [
        [
          125,
          367
        ],
        [
          125,
          370
        ],
        [
          126,
          371
        ],
        [
          127,
          370
        ],
        [
          127,
          368
        ],
        [
          126,
          367
        ]
      ]
    },
    {
      "label": "target",
      "points": [
        [
          426,
          362
        ],
        [
          426,
          363
        ],
        [
          427,
          363
        ],
        [
          427,
          362
        ]
      ]
    },
    {
      "label": "target",
      "points": [
        [
          441,
          356
        ],
        [
          440,
          357
        ],
        [
          442,
          359
        ],
        [
          443,
          359
        ],
        [
          443,
          358
        ]
      ]
    },
    {
      "label": "target",
      "points": [
        [
          461,
          351
        ],
        [
          460,
          352
        ],
        [
          458,
          352
        ],
        [
          457,
          351
        ],
        [
          456,
          351
        ],
        [
          454,
          353
        ],
        [
          453,
          352
        ],
        [
          452,
          352
        ],
        [
          451,
          353
        ],
        [
          450,
          353
        ],
        [
          448,
          355
        ],
        [
          448,
          359
        ],
        [
          451,
          361
        ],
        [
          451,
          362
        ],
        [
          448,
          364
        ],
        [
          448,
          369
        ],
        [
          449,
          370
        ],
        [
          449,
          371
        ],
        [
          450,
          371
        ],
        [
          450,
          370
        ],
        [
          449,
          369
        ],
        [
          451,
          367
        ],
        [
          454,
          367
        ],
        [
          456,
          369
        ],
        [
          456,
          370
        ],
        [
          456,
          369
        ],
        [
          458,
          366
        ],
        [
          458,
          362
        ],
        [
          459,
          361
        ],
        [
          460,
          361
        ],
        [
          460,
          352
        ]
      ]
    },
    {
      "label": "target",
      "points": [
        [
          141,
          332
        ],
        [
          141,
          335
        ],
        [
          143,
          335
        ],
        [
          143,
          333
        ],
        [
          142,
          332
        ]
      ]
    },
    {
      "label": "target",
      "points": [
        [
          150,
          324
        ],
        [
          150,
          325
        ],
        [
          149,
          326
        ],
        [
          149,
          327
        ],
        [
          150,
          328
        ],
        [
          151,
          327
        ],
        [
          151,
          325
        ]
      ]
    },
    {
      "label": "target",
      "points": [
        [
          149,
          318
        ],
        [
          149,
          319
        ],
        [
          150,
          319
        ]
      ]
    },
    {
      "label": "target",
      "points": [
        [
          141,
          315
        ],
        [
          141,
          319
        ],
        [
          143,
          319
        ],
        [
          143,
          317
        ],
        [
          142,
          316
        ],
        [
          142,
          315
        ]
      ]
    },
    {
      "label": "target",
      "points": [
        [
          143,
          279
        ],
        [
          143,
          280
        ],
        [
          142,
          281
        ],
        [
          142,
          282
        ],
        [
          143,
          282
        ]
      ]
    },
    {
      "label": "target",
      "points": [
        [
          391,
          258
        ],
        [
          330,
          274
        ],
        [
          345,
          313
        ],
        [
          312,
          321
        ],
        [
          339,
          342
        ],
        [
          325,
          356
        ],
        [
          308,
          321
        ],
        [
          183,
          337
        ],
        [
          161,
          322
        ],
        [
          156,
          342
        ],
        [
          126,
          342
        ],
        [
          136,
          406
        ],
        [
          124,
          406
        ],
        [
          117,
          471
        ],
        [
          131,
          468
        ],
        [
          132,
          509
        ],
        [
          337,
          511
        ],
        [
          331,
          494
        ],
        [
          356,
          489
        ],
        [
          362,
          465
        ],
        [
          342,
          421
        ],
        [
          313,
          431
        ],
        [
          280,
          408
        ],
        [
          354,
          390
        ],
        [
          347,
          364
        ],
        [
          362,
          376
        ],
        [
          369,
          349
        ],
        [
          360,
          290
        ],
        [
          383,
          339
        ],
        [
          369,
          397
        ],
        [
          416,
          463
        ],
        [
          445,
          384
        ],
        [
          423,
          373
        ],
        [
          424,
          360
        ],
        [
          435,
          366
        ],
        [
          412,
          322
        ],
        [
          454,
          347
        ]
      ]
    },
    {
      "label": "target",
      "points": [
        [
          193,
          242
        ],
        [
          189,
          244
        ],
        [
          185,
          240
        ],
        [
          182,
          249
        ],
        [
          173,
          250
        ],
        [
          170,
          256
        ],
        [
          167,
          252
        ],
        [
          162,
          256
        ],
        [
          162,
          263
        ],
        [
          165,
          265
        ],
        [
          162,
          276
        ],
        [
          160,
          256
        ],
        [
          151,
          257
        ],
        [
          156,
          267
        ],
        [
          146,
          279
        ],
        [
          156,
          284
        ],
        [
          149,
          284
        ],
        [
          147,
          288
        ],
        [
          140,
          289
        ],
        [
          140,
          311
        ],
        [
          143,
          311
        ],
        [
          142,
          297
        ],
        [
          146,
          296
        ],
        [
          148,
          311
        ],
        [
          151,
          312
        ],
        [
          150,
          305
        ],
        [
          155,
          303
        ],
        [
          156,
          313
        ],
        [
          158,
          310
        ],
        [
          161,
          319
        ],
        [
          173,
          268
        ],
        [
          177,
          262
        ],
        [
          173,
          260
        ],
        [
          198,
          255
        ],
        [
          199,
          250
        ],
        [
          196,
          251
        ],
        [
          191,
          246
        ]
      ]
    },
    {
      "label": "target",
      "points": [
        [
          163,
          232
        ],
        [
          162,
          232
        ],
        [
          162,
          238
        ],
        [
          161,
          239
        ],
        [
          161,
          240
        ],
        [
          160,
          241
        ],
        [
          161,
          242
        ],
        [
          163,
          242
        ],
        [
          163,
          241
        ],
        [
          164,
          240
        ],
        [
          164,
          239
        ],
        [
          163,
          238
        ],
        [
          163,
          234
        ],
        [
          164,
          233
        ]
      ]
    }
  ],
  "text": [
    "分割室内右下方散落板件、金属格栅和软管的杂乱地面区域。",
    "标出画面中下部堆有零散施工物料的大片地面。",
    "圈出从中央延伸到右侧、散放多种构件的通行区域。",
    "分割材料散落、可能造成绊倒风险的室内地面范围。",
    "标出现场整理不足并影响通行的板件与软管散放区。",
    "请定位右下方需要清理归整的杂乱施工地面。"
  ],
  "is_sentence": true,
  "source": {
    "split": "train",
    "image_id": 359,
    "file_name": "002__-poor_housekeeping-39-_jpg.rf.70ebf5bc234370cd148edc5447924b6b.jpg",
    "sample_key": "poor_housekeeping",
    "source_category": "poor_housekeeping"
  }
}
