{
  "shapes": [
    {
      "label": "target",
      "points": [
        [
          116,
          318
        ],
        [
          108,
          363
        ],
        [
          109,
          415
        ],
        [
          105,
          423
        ],
        [
          109,
          428
        ],
        [
          109,
          451
        ],
        [
          114,
          449
        ],
        [
          124,
          464
        ],
        [
          128,
          496
        ],
        [
          135,
          474
        ],
        [
          143,
          478
        ],
        [
          152,
          500
        ],
        [
          168,
          502
        ],
        [
          194,
          492
        ],
        [
          213,
          470
        ],
        [
          225,
          466
        ],
        [
          228,
          451
        ],
        [
          219,
          440
        ],
        [
          227,
          398
        ],
        [
          183,
          361
        ],
        [
          170,
          357
        ],
        [
          171,
          340
        ],
        [
          165,
          341
        ],
        [
          161,
          333
        ],
        [
          129,
          317
        ]
      ]
    },
    {
      "label": "target",
      "points": [
        [
          161,
          301
        ],
        [
          161,
          302
        ],
        [
          173,
          302
        ],
        [
          165,
          302
        ],
        [
          164,
          301
        ]
      ]
    },
    {
      "label": "target",
      "points": [
        [
          126,
          300
        ],
        [
          125,
          301
        ],
        [
          125,
          302
        ],
        [
          126,
          302
        ]
      ]
    }
  ],
  "text": [
    "分割画面前景偏左靠墙堆放的一组灰色金属脚手架构件。",
    "标出混凝土墙左下方成捆叠放的金属支撑架和杆件。",
    "圈出画面下部、墙角旁集中堆放的整组灰色脚手架材料。",
    "分割靠墙堆放杂乱、可能影响施工通行的金属脚手架构件。",
    "标出墙边可能造成碰撞或绊倒风险的整组灰色金属支撑材料。",
    "请定位并分割混凝土墙旁需要整理收纳的金属脚手架构件堆。"
  ],
  "is_sentence": true,
  "source": {
    "split": "train",
    "image_id": 299,
    "file_name": "002__-poor_housekeeping-117-_jpg.rf.129052fe1a401a02c9d64e776f0affaf.jpg",
    "sample_key": "poor_housekeeping",
    "source_category": "poor_housekeeping"
  }
}
