{
  "shapes": [
    {
      "label": "target",
      "points": [
        [
          179,
          67
        ],
        [
          161,
          93
        ],
        [
          181,
          139
        ],
        [
          161,
          156
        ],
        [
          159,
          130
        ],
        [
          128,
          132
        ],
        [
          96,
          186
        ],
        [
          127,
          207
        ],
        [
          120,
          218
        ],
        [
          141,
          205
        ],
        [
          170,
          353
        ],
        [
          220,
          508
        ],
        [
          214,
          538
        ],
        [
          248,
          549
        ],
        [
          262,
          536
        ],
        [
          263,
          494
        ],
        [
          238,
          438
        ],
        [
          261,
          366
        ],
        [
          292,
          423
        ],
        [
          290,
          502
        ],
        [
          390,
          521
        ],
        [
          393,
          511
        ],
        [
          344,
          483
        ],
        [
          344,
          313
        ],
        [
          324,
          186
        ],
        [
          256,
          152
        ],
        [
          278,
          114
        ],
        [
          269,
          81
        ],
        [
          221,
          61
        ]
      ]
    }
  ],
  "text": [
    "分割将黄色安全帽搭在肩上的浅蓝衬衫男子。",
    "圈出画面中央戴眼镜、未把安全帽戴在头上的单个人员。",
    "标出侧身站立并用手扶着肩上安全帽的男性。",
    "分割未正确佩戴安全帽、存在头部防护缺失的男子。",
    "标出安全帽放在肩上而非戴好的单个人员。",
    "定位需要正确戴好黄色安全帽的浅蓝衬衫男子。"
  ],
  "is_sentence": true,
  "source": {
    "split": "train",
    "image_id": 268,
    "file_name": "004__IMG_20241113_162035_jpg.rf.4e067fbda470f0c07d79518ece1088c8.jpg",
    "sample_key": "unsafe",
    "source_category": "unsafe"
  }
}
