{
  "shapes": [
    {
      "label": "target",
      "points": [
        [
          316,
          307
        ],
        [
          309,
          325
        ],
        [
          320,
          351
        ],
        [
          280,
          397
        ],
        [
          279,
          411
        ],
        [
          285,
          412
        ],
        [
          288,
          402
        ],
        [
          309,
          388
        ],
        [
          325,
          370
        ],
        [
          327,
          379
        ],
        [
          320,
          414
        ],
        [
          330,
          414
        ],
        [
          338,
          386
        ],
        [
          350,
          398
        ],
        [
          372,
          405
        ],
        [
          364,
          414
        ],
        [
          373,
          415
        ],
        [
          384,
          410
        ],
        [
          390,
          402
        ],
        [
          386,
          392
        ],
        [
          395,
          383
        ],
        [
          391,
          359
        ],
        [
          371,
          340
        ],
        [
          341,
          323
        ],
        [
          330,
          307
        ]
      ]
    }
  ],
  "text": [
    "现场哪些人员存在未戴安全帽的安全隐患?请分割出来。"
  ],
  "is_sentence": true,
  "source": {
    "split": "train",
    "image_id": 112,
    "file_name": "002__-helmet_missing-186-_JPG.rf.1726c9b2b327f55efc9866f57d46df0e.jpg",
    "sample_key": "helmet_missing",
    "source_category": "helmet_missing"
  }
}