{
  "shapes": [
    {
      "label": "target",
      "points": [
        [
          470,
          136
        ],
        [
          427,
          129
        ],
        [
          307,
          135
        ],
        [
          302,
          357
        ],
        [
          319,
          401
        ],
        [
          373,
          397
        ],
        [
          385,
          379
        ],
        [
          438,
          376
        ],
        [
          448,
          349
        ],
        [
          448,
          286
        ],
        [
          455,
          273
        ]
      ]
    }
  ],
  "text": [
    "标出现场材料堆放混乱或文明施工不到位的区域。"
  ],
  "is_sentence": true,
  "source": {
    "split": "train",
    "image_id": 486,
    "file_name": "002__-poor_housekeeping-65-_jpg.rf.5631387269fc76ea9df781daec4fd1b7.jpg",
    "sample_key": "poor_housekeeping",
    "source_category": "poor_housekeeping"
  }
}