{
  "shapes": [
    {
      "label": "target",
      "points": [
        [
          247,
          185
        ],
        [
          229,
          204
        ],
        [
          247,
          252
        ],
        [
          211,
          285
        ],
        [
          210,
          408
        ],
        [
          216,
          420
        ],
        [
          234,
          418
        ],
        [
          261,
          549
        ],
        [
          236,
          589
        ],
        [
          263,
          590
        ],
        [
          300,
          562
        ],
        [
          279,
          479
        ],
        [
          283,
          437
        ],
        [
          333,
          597
        ],
        [
          358,
          609
        ],
        [
          365,
          590
        ],
        [
          351,
          568
        ],
        [
          334,
          415
        ],
        [
          360,
          349
        ],
        [
          339,
          266
        ],
        [
          287,
          243
        ],
        [
          283,
          193
        ]
      ]
    }
  ],
  "text": [
    "标出未按要求穿戴反光背心的工人。"
  ],
  "is_sentence": true,
  "source": {
    "split": "train",
    "image_id": 247,
    "file_name": "004__IMG_20241113_162035193_jpg.rf.a9ea31c371f2e1a16c3f79932b5c0281.jpg",
    "sample_key": "no_jacket",
    "source_category": "no jacket"
  }
}