{
  "shapes": [
    {
      "label": "target",
      "points": [
        [
          112,
          407
        ],
        [
          108,
          408
        ],
        [
          99,
          417
        ],
        [
          81,
          442
        ],
        [
          91,
          472
        ],
        [
          97,
          511
        ],
        [
          119,
          511
        ],
        [
          120,
          491
        ],
        [
          114,
          461
        ],
        [
          118,
          428
        ],
        [
          116,
          424
        ],
        [
          115,
          410
        ]
      ]
    },
    {
      "label": "target",
      "points": [
        [
          136,
          330
        ],
        [
          136,
          334
        ],
        [
          135,
          335
        ],
        [
          135,
          336
        ],
        [
          134,
          337
        ],
        [
          134,
          338
        ],
        [
          136,
          340
        ],
        [
          136,
          342
        ],
        [
          137,
          343
        ],
        [
          139,
          343
        ],
        [
          140,
          342
        ],
        [
          140,
          339
        ],
        [
          139,
          338
        ],
        [
          139,
          337
        ],
        [
          138,
          336
        ],
        [
          138,
          333
        ],
        [
          137,
          332
        ],
        [
          137,
          330
        ]
      ]
    },
    {
      "label": "target",
      "points": [
        [
          223,
          309
        ],
        [
          216,
          308
        ],
        [
          203,
          320
        ],
        [
          200,
          327
        ],
        [
          189,
          336
        ],
        [
          164,
          342
        ],
        [
          161,
          345
        ],
        [
          159,
          353
        ],
        [
          152,
          357
        ],
        [
          148,
          366
        ],
        [
          149,
          371
        ],
        [
          154,
          373
        ],
        [
          176,
          367
        ],
        [
          206,
          347
        ],
        [
          213,
          346
        ],
        [
          223,
          341
        ],
        [
          227,
          333
        ]
      ]
    },
    {
      "label": "target",
      "points": [
        [
          113,
          191
        ],
        [
          104,
          196
        ],
        [
          73,
          229
        ],
        [
          65,
          241
        ],
        [
          59,
          262
        ],
        [
          63,
          306
        ],
        [
          70,
          325
        ],
        [
          70,
          344
        ],
        [
          82,
          408
        ],
        [
          114,
          374
        ],
        [
          111,
          333
        ],
        [
          119,
          300
        ]
      ]
    },
    {
      "label": "target",
      "points": [
        [
          158,
          173
        ],
        [
          136,
          176
        ],
        [
          126,
          184
        ],
        [
          132,
          306
        ],
        [
          148,
          314
        ],
        [
          153,
          310
        ],
        [
          151,
          283
        ],
        [
          156,
          265
        ],
        [
          166,
          265
        ],
        [
          172,
          271
        ],
        [
          172,
          291
        ],
        [
          178,
          284
        ],
        [
          183,
          284
        ],
        [
          188,
          294
        ],
        [
          194,
          297
        ],
        [
          198,
          286
        ],
        [
          190,
          274
        ],
        [
          211,
          258
        ],
        [
          215,
          246
        ],
        [
          214,
          230
        ],
        [
          208,
          216
        ],
        [
          185,
          201
        ],
        [
          173,
          208
        ],
        [
          173,
          184
        ]
      ]
    }
  ],
  "text": [
    "圈出高处作业但没有系安全带的人员。"
  ],
  "is_sentence": true,
  "source": {
    "split": "train",
    "image_id": 340,
    "file_name": "002__-harness_missing-99-_JPG.rf.c9cbcb4708c3f058b2ea6ac943e3aee2.jpg",
    "sample_key": "harness_missing",
    "source_category": "harness_missing"
  }
}